{"name":"login exitoso","id":"login;login-exitoso","testSteps":[{"number":1,"description":"Given que quiero iniciar sesion","duration":10928,"startTime":"2021-10-23T17:19:31.405-05:00[America/Bogota]","screenshots":[{"screenshot":"865e805b3add30969ff2539f3192c312fada21bfe540e3ce4fb73b783f344720.png","timeStamp":1635027582333}],"result":"SUCCESS","precondition":false,"level":0,"children":[{"number":2,"description":"Chillin open landin page","duration":3771,"startTime":"2021-10-23T17:19:38.219-05:00[America/Bogota]","screenshots":[{"screenshot":"a8fd6ded05954b9049ffbb7e32249db53abf191e7939710e56449b06d210a1d6.png","timeStamp":1635027578834},{"screenshot":"865e805b3add30969ff2539f3192c312fada21bfe540e3ce4fb73b783f344720.png","timeStamp":1635027581990}],"result":"SUCCESS","precondition":false,"level":1,"children":[{"number":3,"description":"Chillin opens the Landing page","duration":3110,"startTime":"2021-10-23T17:19:38.859-05:00[America/Bogota]","screenshots":[{"screenshot":"a8fd6ded05954b9049ffbb7e32249db53abf191e7939710e56449b06d210a1d6.png","timeStamp":1635027579107},{"screenshot":"865e805b3add30969ff2539f3192c312fada21bfe540e3ce4fb73b783f344720.png","timeStamp":1635027581968}],"result":"SUCCESS","precondition":false,"level":2}]}]},{"number":4,"description":"When ingrese las credenciales correctas","duration":8584,"startTime":"2021-10-23T17:19:42.335-05:00[America/Bogota]","screenshots":[{"screenshot":"f5debf6003b5105c1c3efb09f71fe647511798e798d9c7a8ea74b44286a048fd.png","timeStamp":1635027590919}],"result":"SUCCESS","precondition":false,"level":0,"children":[{"number":5,"description":"Chillin do login","duration":8504,"startTime":"2021-10-23T17:19:42.395-05:00[America/Bogota]","screenshots":[{"screenshot":"f5debf6003b5105c1c3efb09f71fe647511798e798d9c7a8ea74b44286a048fd.png","timeStamp":1635027590899}],"result":"SUCCESS","precondition":false,"level":1,"children":[{"number":6,"description":"Chillin clears field user name","duration":881,"startTime":"2021-10-23T17:19:42.959-05:00[America/Bogota]","screenshots":[{"screenshot":"60636235085c0b0a69c8f084ea6d5dbf7a2d2863b4365c69f3c46433896d31e2.png","timeStamp":1635027583338},{"screenshot":"246bb93833d3fb3bc4643944ea4fe18cc1f8d039fd884a65d17d8b48ed32f201.png","timeStamp":1635027583839}],"result":"SUCCESS","precondition":false,"level":2},{"number":7,"description":"Chillin enters \u0027Admin\u0027 into user name","duration":857,"startTime":"2021-10-23T17:19:43.842-05:00[America/Bogota]","screenshots":[{"screenshot":"246bb93833d3fb3bc4643944ea4fe18cc1f8d039fd884a65d17d8b48ed32f201.png","timeStamp":1635027583861},{"screenshot":"d7846fc2a9a229a368e00260248f1e72717c74ed04bdfedb0b38b45c819339d1.png","timeStamp":1635027584699}],"result":"SUCCESS","precondition":false,"level":2},{"number":8,"description":"Chillin clears field Password","duration":1146,"startTime":"2021-10-23T17:19:44.838-05:00[America/Bogota]","screenshots":[{"screenshot":"669b316816d3a9a098b0f35c6a538b2d388335b6253083bd21b22f71eaf5c647.png","timeStamp":1635027585285},{"screenshot":"e7a0c7b8387980d2c9939e46153ef79099a41b82b4c3a6eb69a9e61f42ca6d48.png","timeStamp":1635027585984}],"result":"SUCCESS","precondition":false,"level":2},{"number":9,"description":"Chillin enters \u0027admin123\u0027 into Password","duration":846,"startTime":"2021-10-23T17:19:45.986-05:00[America/Bogota]","screenshots":[{"screenshot":"e7a0c7b8387980d2c9939e46153ef79099a41b82b4c3a6eb69a9e61f42ca6d48.png","timeStamp":1635027586009},{"screenshot":"1616dcd7c6c585640a80159f0ba247655367210b52efc7a58df805c60632a519.png","timeStamp":1635027586832}],"result":"SUCCESS","precondition":false,"level":2},{"number":10,"description":"Chillin clicks on boton login","duration":3910,"startTime":"2021-10-23T17:19:46.969-05:00[America/Bogota]","screenshots":[{"screenshot":"1616dcd7c6c585640a80159f0ba247655367210b52efc7a58df805c60632a519.png","timeStamp":1635027587254},{"screenshot":"f5debf6003b5105c1c3efb09f71fe647511798e798d9c7a8ea74b44286a048fd.png","timeStamp":1635027590879}],"result":"SUCCESS","precondition":false,"level":2}]}]},{"number":11,"description":"Then deberia logearme correctamente","duration":1226,"startTime":"2021-10-23T17:19:50.921-05:00[America/Bogota]","screenshots":[{"screenshot":"f5debf6003b5105c1c3efb09f71fe647511798e798d9c7a8ea74b44286a048fd.png","timeStamp":1635027592147}],"result":"SUCCESS","precondition":false,"level":0,"children":[{"number":12,"description":"Then login should be (true)","duration":644,"startTime":"2021-10-23T17:19:51.486-05:00[America/Bogota]","screenshots":[{"screenshot":"f5debf6003b5105c1c3efb09f71fe647511798e798d9c7a8ea74b44286a048fd.png","timeStamp":1635027592130}],"result":"SUCCESS","precondition":false,"level":1}]}],"userStory":{"id":"login","storyName":"login","path":"file:///D:/DANIEL/Sofka/Automaización%20de%20pruebas/retos_serenity/web_ui/RETO_WEBUI/src/test/resources/features/orange_hrm/login/login.feature","narrative":"  yo como usuario administraor deseo loggearme en la pagina para realizar cambios\n  en la base de datos de recursos humanos de OrangeHRM","type":"feature"},"featureTag":{"name":"Login/login","type":"feature","displayName":"Login/login"},"title":"login exitoso","tags":[{"name":"Orange hrm","type":"theme","displayName":"Orange hrm"},{"name":"Login/login","type":"feature","displayName":"login"},{"name":"Orange hrm/Login","type":"capability","displayName":"Login"}],"startTime":"2021-10-23T17:19:31.092-05:00[America/Bogota]","duration":21057,"projectKey":"","sessionId":"9aa9773493c5ee58b1df6de1ad59933d","driver":"chrome","isManualTestingUpToDate":false,"manual":false,"testSource":"Cucumber","actors":[{"name":"Chillin","can":["browse the web"]}],"result":"SUCCESS"}